cfuse_core.cpython-311-darwin.so
optimize_basin.py
cfuse/__init__.py
cfuse/cli.py
cfuse/config.py
cfuse/io.py
cfuse/legacy.py
cfuse/netcdf.py
cfuse/torch.py
cfuse-0.4.1.dist-info/licenses/LICENSE
cfuse-0.4.1.dist-info/METADATA
cfuse-0.4.1.dist-info/WHEEL
cfuse-0.4.1.dist-info/entry_points.txt
cfuse-0.4.1.dist-info/top_level.txt
cfuse-0.4.1.dist-info/RECORD
