Metadata-Version: 2.4
Name: cfuse
Version: 0.4.1
Summary: Differentiable FUSE hydrological model with Enzyme AD
Author-email: Darri Eythorsson <darri.eythorsson@ucalgary.ca>
License-Expression: MIT
Project-URL: Homepage, https://github.com/DarriEy/cFUSE
Project-URL: Repository, https://github.com/DarriEy/cFUSE
Project-URL: Issues, https://github.com/DarriEy/cFUSE/issues
Keywords: hydrology,automatic-differentiation,fuse,enzyme
Classifier: Development Status :: 4 - Beta
Classifier: Intended Audience :: Science/Research
Classifier: Programming Language :: Python :: 3
Classifier: Programming Language :: Python :: 3.9
Classifier: Programming Language :: Python :: 3.10
Classifier: Programming Language :: Python :: 3.11
Classifier: Programming Language :: Python :: 3.12
Classifier: Programming Language :: C++
Classifier: Topic :: Scientific/Engineering :: Hydrology
Requires-Python: >=3.9
License-File: LICENSE
Requires-Dist: numpy>=1.20
Requires-Dist: torch>=2.0
Requires-Dist: netCDF4>=1.5
Requires-Dist: tqdm>=4.0
Requires-Dist: matplotlib>=3.0
Provides-Extra: dev
Requires-Dist: pytest>=7.0; extra == "dev"
Requires-Dist: pytest-cov>=4.0; extra == "dev"
Dynamic: license-file
